selcuk_cihan/__init__.py
selcuk_cihan-0.0.1.dist-info/METADATA
selcuk_cihan-0.0.1.dist-info/WHEEL
selcuk_cihan-0.0.1.dist-info/top_level.txt
selcuk_cihan-0.0.1.dist-info/RECORD
